<?xml version="1.0" encoding="utf-8" ?>
<Defs>
	<BodyPartDef>
		<defName>MechanicalJaw</defName>
		<label>jaw</label>
		<hitPoints>20</hitPoints>
		<permanentInjuryChanceFactor>0</permanentInjuryChanceFactor>
		<skinCovered>false</skinCovered>
		<solid>true</solid>
		<bleedRate>0</bleedRate>
		<alive>false</alive>
		<tags>
			<li>EatingSource</li>
		</tags>
	</BodyPartDef>

	<BodyPartDef>
		<defName>VoxEmitter</defName>
		<label>vox emitter</label>
		<hitPoints>10</hitPoints>
		<permanentInjuryChanceFactor>0</permanentInjuryChanceFactor>
		<skinCovered>false</skinCovered>
		<solid>true</solid>
		<alive>false</alive>
		<bleedRate>0</bleedRate>
		<tags>
			<li>TalkingSource</li>
		</tags>
	</BodyPartDef>
	  
	<BodyPartDef>
    	<defName>Battery</defName>
    	<label>battery</label>
    	<hitPoints>15</hitPoints>
    	<permanentInjuryChanceFactor>0</permanentInjuryChanceFactor>
    	<skinCovered>false</skinCovered>
    	<solid>true</solid>
    	<alive>false</alive>
    	<bleedRate>0</bleedRate>
    	<tags>
      		<li>BloodPumpingSource</li>
    	</tags>
	</BodyPartDef>

	<BodyPartDef>
		<defName>BetterMechanicalFinger</defName>
		<label>finger</label>
		<hitPoints>8</hitPoints>
		<frostbiteVulnerability>10</frostbiteVulnerability>
		<permanentInjuryChanceFactor>0</permanentInjuryChanceFactor>
		<skinCovered>false</skinCovered>
		<solid>true</solid>
		<alive>false</alive>
		<bleedRate>0</bleedRate>
		<pawnGeneratorCanAmputate>true</pawnGeneratorCanAmputate>
		<tags>
			<li>ManipulationLimbDigit</li>
		</tags>
	</BodyPartDef>

	<BodyPartDef>
		<defName>BetterHearingSensor</defName>
		<label>sound sensor</label>
		<hitPoints>12</hitPoints>
		<frostbiteVulnerability>2</frostbiteVulnerability>
		<permanentInjuryChanceFactor>0</permanentInjuryChanceFactor>
		<skinCovered>false</skinCovered>
		<solid>true</solid>
		<alive>false</alive>
		<bleedRate>0</bleedRate>
		<tags>
			<li>HearingSource</li>
		</tags>
	</BodyPartDef>
<!--
	<BodyPartDef>
		<defName>MechanicalThoraxPlating</defName>
		<label>thorax plating</label>
		<hitPoints>40</hitPoints>
		<permanentInjuryChanceFactor>0</permanentInjuryChanceFactor>
		<skinCovered>false</skinCovered>
		<solid>true</solid>
		<alive>false</alive>
		<bleedRate>0</bleedRate>
	</BodyPartDef>

	<BodyPartDef>
		<defName>MechancialHeadPlating</defName>
		<label>head plating</label>
		<hitPoints>30</hitPoints>
		<permanentInjuryChanceFactor>0</permanentInjuryChanceFactor>
		<skinCovered>false</skinCovered>
		<solid>true</solid>
		<alive>false</alive>
		<bleedRate>0</bleedRate>
	</BodyPartDef>
-->	
	<BodyPartDef>
		<defName>ArtificialBrainCasing</defName>
		<label>artifical brain casing</label>
		<hitPoints>25</hitPoints>
		<permanentInjuryChanceFactor>0</permanentInjuryChanceFactor>
		<skinCovered>false</skinCovered>
		<solid>true</solid>
		<alive>false</alive>
		<bleedRate>0</bleedRate>
		<destroyableByDamage>false</destroyableByDamage>
	</BodyPartDef>
<!--
	<BodyPartDef>
		<defName>MechanicalHandPlating</defName>
		<label>hand plating</label>
		<hitPoints>20</hitPoints>
		<permanentInjuryChanceFactor>0</permanentInjuryChanceFactor>
		<skinCovered>false</skinCovered>
		<solid>true</solid>
		<alive>false</alive>
		<bleedRate>0</bleedRate>
	</BodyPartDef>

	<BodyPartDef>
		<defName>MechanicalFingerPlating</defName>
		<label>finger plating</label>
		<hitPoints>10</hitPoints>
		<permanentInjuryChanceFactor>0</permanentInjuryChanceFactor>
		<skinCovered>false</skinCovered>
		<solid>true</solid>
		<alive>false</alive>
		<bleedRate>0</bleedRate>
	</BodyPartDef>

	<BodyPartDef>
		<defName>MechanicalShoulderMotor</defName>
		<label>shoulder motor</label>
		<hitPoints>20</hitPoints>
		<permanentInjuryChanceFactor>0</permanentInjuryChanceFactor>
		<skinCovered>false</skinCovered>
		<solid>true</solid>
		<alive>false</alive>
		<bleedRate>0</bleedRate>
		<tags>
			<li>ManipulationLimbSegment</li>
		</tags>
	</BodyPartDef>

	<BodyPartDef>
		<defName>MechanicalElbowMotor</defName>
		<label>elbow motor</label>
		<hitPoints>20</hitPoints>
		<permanentInjuryChanceFactor>0</permanentInjuryChanceFactor>
		<skinCovered>false</skinCovered>
		<solid>true</solid>
		<alive>false</alive>
		<bleedRate>0</bleedRate>
		<tags>
			<li>ManipulationLimbCore</li>
		</tags>
	</BodyPartDef>

	<BodyPartDef>
		<defName>MechanicalMotorLeg</defName>
		<label>limb motor</label>
		<hitPoints>20</hitPoints>
		<permanentInjuryChanceFactor>0</permanentInjuryChanceFactor>
		<skinCovered>false</skinCovered>
		<solid>true</solid>
		<alive>false</alive>
		<bleedRate>0</bleedRate>
		<tags>
			<li>MovingLimbCore</li>
		</tags>
	</BodyPartDef>

	<BodyPartDef>
		<defName>MechanicalMotorKnee</defName>
		<label>limb motor</label>
		<hitPoints>20</hitPoints>
		<permanentInjuryChanceFactor>0</permanentInjuryChanceFactor>
		<skinCovered>false</skinCovered>
		<solid>true</solid>
		<alive>false</alive>
		<bleedRate>0</bleedRate>
		<tags>
			<li>MovingLimbSegment</li>
		</tags>
	</BodyPartDef>

	<BodyPartDef>
		<defName>MechanicalLimbMotorPlating</defName>
		<label>limb motor plating</label>
		<hitPoints>20</hitPoints>
		<permanentInjuryChanceFactor>0</permanentInjuryChanceFactor>
		<skinCovered>false</skinCovered>
		<solid>true</solid>
		<alive>false</alive>
		<bleedRate>0</bleedRate>
	</BodyPartDef>

	<BodyPartDef>
		<defName>MechanicalLimbSegment</defName>
		<label>limb segment</label>
		<hitPoints>20</hitPoints>
		<permanentInjuryChanceFactor>0</permanentInjuryChanceFactor>
		<skinCovered>false</skinCovered>
		<solid>true</solid>
		<alive>false</alive>
		<bleedRate>0</bleedRate>
	</BodyPartDef>

	<BodyPartDef>
		<defName>MechanicalLimbSegmentPlating</defName>
		<label>limb segment plating</label>
		<hitPoints>30</hitPoints>
		<permanentInjuryChanceFactor>0</permanentInjuryChanceFactor>
		<skinCovered>false</skinCovered>
		<solid>true</solid>
		<alive>false</alive>
		<bleedRate>0</bleedRate>
	</BodyPartDef>
-->
	<BodyPartDef>
		<defName>BetterMechanicalFoot</defName>
		<label>foot</label>
		<hitPoints>25</hitPoints>
		<frostbiteVulnerability>2</frostbiteVulnerability>
		<permanentInjuryChanceFactor>0</permanentInjuryChanceFactor>
		<skinCovered>false</skinCovered>
		<solid>true</solid>
		<alive>false</alive>
		<bleedRate>0</bleedRate>
		<tags>
			<li>MovingLimbSegment</li>
		</tags>
	</BodyPartDef>
<!--
	<BodyPartDef>
		<defName>MechanicalFootPlating</defName>
		<label>foot plating</label>
		<hitPoints>25</hitPoints>
		<permanentInjuryChanceFactor>0</permanentInjuryChanceFactor>
		<skinCovered>false</skinCovered>
		<solid>true</solid>
		<alive>false</alive>
		<bleedRate>0</bleedRate>
	</BodyPartDef>
-->
	<BodyPartDef>
		<defName>MechanicalToe</defName>
		<label>toe</label>
		<hitPoints>8</hitPoints>
		<permanentInjuryChanceFactor>0</permanentInjuryChanceFactor>
		<skinCovered>false</skinCovered>
		<solid>true</solid>
		<alive>false</alive>
		<bleedRate>0</bleedRate>
		<tags>
			<li>MovingLimbDigit</li>
		</tags>
	</BodyPartDef>
<!--
	<BodyPartDef>
		<defName>MechanicalToePlating</defName>
		<label>toe plating</label>
		<hitPoints>8</hitPoints>
		<permanentInjuryChanceFactor>0</permanentInjuryChanceFactor>
		<skinCovered>false</skinCovered>
		<solid>true</solid>
		<alive>false</alive>
		<bleedRate>0</bleedRate>
	</BodyPartDef>

	<BodyPartDef>
		<defName>MechanicalUpperThorax</defName>
		<label>upper thorax</label>
		<hitPoints>30</hitPoints>
		<permanentInjuryChanceFactor>0</permanentInjuryChanceFactor>
		<skinCovered>false</skinCovered>
		<solid>true</solid>
		<alive>false</alive>
		<bleedRate>0</bleedRate>
	</BodyPartDef>

	<BodyPartDef>
		<defName>MechanicalLowerThorax</defName>
		<label>lower thorax</label>
		<hitPoints>30</hitPoints>
		<permanentInjuryChanceFactor>0</permanentInjuryChanceFactor>
		<skinCovered>false</skinCovered>
		<solid>true</solid>	
		<alive>false</alive>
		<bleedRate>0</bleedRate>
	</BodyPartDef>
-->
	<BodyPartDef>
		<defName>MechanicalClavicle</defName>
		<label>shoulder framework</label>
		<hitPoints>25</hitPoints>
		<permanentInjuryChanceFactor>0</permanentInjuryChanceFactor>
		<skinCovered>false</skinCovered>
		<solid>true</solid>
		<alive>false</alive>
		<bleedRate>0</bleedRate>
		<tags>
			<li>ManipulationLimbSegment</li>
		</tags>
		<destroyableByDamage>false</destroyableByDamage>
	</BodyPartDef>

	<BodyPartDef>
		<defName>MechanicalHumerus</defName>
		<label>upper arm framework</label>
		<hitPoints>25</hitPoints>
		<permanentInjuryChanceFactor>0</permanentInjuryChanceFactor>
		<skinCovered>0</skinCovered>
		<solid>true</solid>
		<alive>false</alive>
		<bleedRate>0</bleedRate>
		<tags>
			<li>ManipulationLimbSegment</li>
		</tags>
	</BodyPartDef>

	<BodyPartDef>
		<defName>MechanicalRadius</defName>
		<label>lower arm framework</label>
		<hitPoints>20</hitPoints>
		<permanentInjuryChanceFactor>0</permanentInjuryChanceFactor>
		<skinCovered>0</skinCovered>
		<solid>true</solid>
		<alive>false</alive>
		<bleedRate>0</bleedRate>
		<tags>
			<li>ManipulationLimbSegment</li>
		</tags>
	</BodyPartDef>

	<BodyPartDef>
		<defName>MechanicalFemur</defName>
		<label>upper leg framework</label>
		<hitPoints>25</hitPoints>
		<permanentInjuryChanceFactor>0</permanentInjuryChanceFactor>
		<skinCovered>0</skinCovered>
		<solid>true</solid>
		<alive>false</alive>
		<bleedRate>0</bleedRate>
		<tags>
			<li>MovingLimbSegment</li>
		</tags>
	</BodyPartDef>

	<BodyPartDef>
		<defName>MechanicalTibia</defName>
		<label>lower leg framework</label>
		<hitPoints>25</hitPoints>
		<permanentInjuryChanceFactor>0</permanentInjuryChanceFactor>
		<skinCovered>0</skinCovered>
		<solid>true</solid>
		<alive>false</alive>
		<bleedRate>0</bleedRate>
		<tags>
			<li>MovingLimbSegment</li>
		</tags>
	</BodyPartDef>

	<BodyPartDef>
		<defName>MechanicalRibcage</defName>
		<label>chest framework</label>
		<hitPoints>30</hitPoints>
		<permanentInjuryChanceFactor>0</permanentInjuryChanceFactor>
		<skinCovered>false</skinCovered>
		<solid>true</solid>
		<alive>false</alive>
		<bleedRate>0</bleedRate>
		<!--
		<tags>
			<li>BreathingSourceCage</li>
		</tags>
		-->
		<destroyableByDamage>false</destroyableByDamage>
	</BodyPartDef>

	<BodyPartDef>
		<defName>MechanicalSternum</defName>
		<label>chest bracing</label>
		<hitPoints>20</hitPoints>
		<permanentInjuryChanceFactor>0</permanentInjuryChanceFactor>
		<skinCovered>false</skinCovered>
		<solid>true</solid>
		<alive>false</alive>
		<bleedRate>0</bleedRate>
		<!--
		<tags>
			<li>BreathingSourceCage</li>
		</tags>
		-->
		<destroyableByDamage>false</destroyableByDamage>
	</BodyPartDef>

	<BodyPartDef>
		<defName>MechanicalSpine</defName>
		<label>nexus</label>
		<hitPoints>25</hitPoints>
		<permanentInjuryChanceFactor>0</permanentInjuryChanceFactor>
		<skinCovered>false</skinCovered>
		<solid>true</solid>
		<bleedRate>0</bleedRate>
		<alive>false</alive>
		<tags>
			<li>Spine</li>
		</tags>
	</BodyPartDef>

	<BodyPartDef>
		<defName>MechanicalPelvis</defName>
		<label>midsection</label>
		<hitPoints>25</hitPoints>
		<permanentInjuryChanceFactor>0</permanentInjuryChanceFactor>
		<skinCovered>false</skinCovered>
		<solid>true</solid>
		<alive>false</alive>
		<bleedRate>0</bleedRate>
		<tags>
			<li>Pelvis</li>
		</tags>
		<destroyableByDamage>false</destroyableByDamage>
	</BodyPartDef>

</Defs>